MANIFEST.in
README.rst
setup.cfg
setup.py
zopeskel.txt
docs/HISTORY.rst
docs/LICENSE.GPL
docs/LICENSE.txt
pmr2/__init__.py
pmr2.z3cform.egg-info/PKG-INFO
pmr2.z3cform.egg-info/SOURCES.txt
pmr2.z3cform.egg-info/dependency_links.txt
pmr2.z3cform.egg-info/entry_points.txt
pmr2.z3cform.egg-info/namespace_packages.txt
pmr2.z3cform.egg-info/not-zip-safe
pmr2.z3cform.egg-info/paster_plugins.txt
pmr2.z3cform.egg-info/requires.txt
pmr2.z3cform.egg-info/top_level.txt
pmr2/z3cform/__init__.py
pmr2/z3cform/configure.zcml
pmr2/z3cform/form.py
pmr2/z3cform/form.rst
pmr2/z3cform/i18n.py
pmr2/z3cform/interfaces.py
pmr2/z3cform/page.py
pmr2/z3cform/page.rst
pmr2/z3cform/profiles.zcml
pmr2/z3cform/templates.py
pmr2/z3cform/testing.py
pmr2/z3cform/profiles/default/browserlayer.xml
pmr2/z3cform/profiles/default/metadata.xml
pmr2/z3cform/templates/form.pt
pmr2/z3cform/templates/page.pt
pmr2/z3cform/templates/plain-main-macros.pt
pmr2/z3cform/templates/plone-main-macros.pt
pmr2/z3cform/templates/plone-z3cform-macros-ex.pt
pmr2/z3cform/templates/wrapped_form.pt
pmr2/z3cform/tests/__init__.py
pmr2/z3cform/tests/base.py
pmr2/z3cform/tests/form.pt
pmr2/z3cform/tests/templates.py
pmr2/z3cform/tests/test_doctest.py
pmr2/z3cform/tests/test_setup.py
pmr2/z3cform/tests/testing.zcml