Metadata-Version: 1.1
Name: pmr2.z3cform
Version: 0.3.1
Summary: Customized z3c.form and plone.z3cform library for PMR2
Home-page: https://github.com/PMR2/pmr2.z3cform
Author: Tommy Yu
Author-email: tommy.yu@auckland.ac.nz
License: GPL
Platform: UNKNOWN
Classifier: Programming Language :: Python
Classifier: Topic :: Software Development :: Libraries :: Python Modules
